postgreasy/__init__.py
postgreasy/postgres_connection.py
postgreasy-1.1.1.dist-info/LICENSE
postgreasy-1.1.1.dist-info/METADATA
postgreasy-1.1.1.dist-info/WHEEL
postgreasy-1.1.1.dist-info/top_level.txt
postgreasy-1.1.1.dist-info/RECORD
