Metadata-Version: 2.2
Name: postgreasy
Version: 1.1.1
Summary: A simple package for interacting with a Postgres Database.
Author-email: Casper Kole <casper@voltgoed.nl>
Project-URL: Homepage, https://github.com/CFKaligula/postgreasy
Project-URL: Issues, https://github.com/CFKaligula/postgreasy/issues
Classifier: Programming Language :: Python :: 3
Classifier: License :: OSI Approved :: MIT License
Classifier: Operating System :: OS Independent
Requires-Python: >=3.10
License-File: LICENSE
Requires-Dist: pandas
Requires-Dist: psycopg2-binary
Requires-Dist: python-dotenv
